threads_scraper/__init__.py
threads_scraper/scraper.py
threads_scraper-1.1.0.dist-info/LICENSE
threads_scraper-1.1.0.dist-info/METADATA
threads_scraper-1.1.0.dist-info/WHEEL
threads_scraper-1.1.0.dist-info/top_level.txt
threads_scraper-1.1.0.dist-info/RECORD
