Metadata-Version: 2.1
Name: threads-scraper
Version: 1.1.0
Summary: A Python package for scraping Threads posts.
Home-page: https://github.com/ChenBingWei1201/threads_scraper
Author: ChenBingWei1201
Author-email: rain4030633@gmail.com
Classifier: Programming Language :: Python :: 3
Classifier: License :: OSI Approved :: MIT License
Classifier: Operating System :: OS Independent
Requires-Python: >=3.7
License-File: LICENSE
Requires-Dist: selenium >=4.0.0
Requires-Dist: pandas >=1.0.0
Requires-Dist: python-dotenv >=0.20.0
